rheo/__init__.py
rheo/app.py
rheo/cli/__init__.py
rheo/cli/app.py
rheo/cli/commands/__init__.py
rheo/cli/commands/download.py
rheo/cli/main.py
rheo/cli/output/__init__.py
rheo/cli/output/progress.py
rheo/cli/state.py
rheo/cli/utils.py
rheo/config/__init__.py
rheo/config/settings.py
rheo/domain/__init__.py
rheo/domain/cancellation.py
rheo/domain/downloads.py
rheo/domain/exceptions.py
rheo/domain/file_config.py
rheo/domain/hash_validation.py
rheo/domain/retry.py
rheo/domain/speed.py
rheo/downloads/__init__.py
rheo/downloads/destination_resolver.py
rheo/downloads/manager.py
rheo/downloads/queue.py
rheo/downloads/retry/__init__.py
rheo/downloads/retry/base.py
rheo/downloads/retry/categoriser.py
rheo/downloads/retry/handler.py
rheo/downloads/retry/null.py
rheo/downloads/validation/__init__.py
rheo/downloads/validation/base.py
rheo/downloads/validation/null.py
rheo/downloads/validation/validator.py
rheo/downloads/worker/__init__.py
rheo/downloads/worker/base.py
rheo/downloads/worker/factory.py
rheo/downloads/worker/worker.py
rheo/downloads/worker_pool/__init__.py
rheo/downloads/worker_pool/base.py
rheo/downloads/worker_pool/factory.py
rheo/downloads/worker_pool/pool.py
rheo/events/__init__.py
rheo/events/base.py
rheo/events/emitter.py
rheo/events/models/__init__.py
rheo/events/models/base.py
rheo/events/models/download.py
rheo/events/models/error_info.py
rheo/events/null.py
rheo/events/subscription.py
rheo/events/worker_events.py
rheo/infrastructure/__init__.py
rheo/infrastructure/http/__init__.py
rheo/infrastructure/http/aiohttp_client.py
rheo/infrastructure/http/base.py
rheo/infrastructure/http/factories.py
rheo/infrastructure/logging.py
rheo/tracking/__init__.py
rheo/tracking/base.py
rheo/tracking/null.py
rheo/tracking/tracker.py
rheo/utils/__init__.py
rheopy-0.7.0.dist-info/METADATA
rheopy-0.7.0.dist-info/WHEEL
rheopy-0.7.0.dist-info/entry_points.txt
rheopy-0.7.0.dist-info/licenses/LICENSE
rheopy-0.7.0.dist-info/RECORD
