Metadata-Version: 2.4
Name: rheopy
Version: 0.7.0
Summary: Concurrent HTTP download orchestration with async I/O
License: MIT
License-File: LICENSE
Keywords: async,asyncio,download,downloader,http,concurrent,aiohttp,cli
Author: plutopulp
Author-email: plutopulped@gmail.com
Requires-Python: >=3.11,<4.0
Classifier: Development Status :: 3 - Alpha
Classifier: Intended Audience :: Developers
Classifier: License :: OSI Approved :: MIT License
Classifier: Programming Language :: Python :: 3
Classifier: Programming Language :: Python :: 3.11
Classifier: Programming Language :: Python :: 3.12
Classifier: Programming Language :: Python :: 3.13
Classifier: Programming Language :: Python :: 3.14
Classifier: Topic :: Software Development :: Libraries :: Python Modules
Classifier: Topic :: Internet :: WWW/HTTP
Classifier: Framework :: AsyncIO
Classifier: Operating System :: OS Independent
Classifier: Typing :: Typed
Provides-Extra: dev
Requires-Dist: aiofiles (>=25.1.0,<26.0.0)
Requires-Dist: aiohttp (>=3.12.15,<4.0.0)
Requires-Dist: aioresponses (>=0.7.8,<0.8.0) ; extra == "dev"
Requires-Dist: black (>=25.11.0,<26.0.0) ; extra == "dev"
Requires-Dist: blockbuster (>=1.5.25,<2.0.0) ; extra == "dev"
Requires-Dist: certifi (>=2025.11.12)
Requires-Dist: flake8 (>=7.3.0,<8.0.0) ; extra == "dev"
Requires-Dist: isort (>=7.0.0,<8.0.0) ; extra == "dev"
Requires-Dist: loguru (>=0.7.3,<0.8.0)
Requires-Dist: mypy (>=1.11.0,<2.0.0) ; extra == "dev"
Requires-Dist: pydantic (>=2.12.4,<3.0.0)
Requires-Dist: pydantic-settings (>=2.12.0,<3.0.0)
Requires-Dist: pytest (>=9.0.1,<10.0.0) ; extra == "dev"
Requires-Dist: pytest-asyncio (>=1.2.0,<2.0.0) ; extra == "dev"
Requires-Dist: pytest-benchmark (>=5.2.3,<6.0.0) ; extra == "dev"
Requires-Dist: pytest-cov (>=7.0.0,<8.0.0) ; extra == "dev"
Requires-Dist: pytest-mock (>=3.12.0,<4.0.0) ; extra == "dev"
Requires-Dist: rich (>=14.2.0,<15.0.0)
Requires-Dist: typer (>=0.20.0,<0.21.0)
Requires-Dist: types-aiofiles (>=25.1.0.20251011) ; extra == "dev"
Project-URL: Bug Tracker, https://github.com/plutopulp/rheo/issues
Project-URL: Changelog, https://github.com/plutopulp/rheo/blob/main/CHANGELOG.md
Project-URL: Documentation, https://github.com/plutopulp/rheo#readme
Project-URL: Homepage, https://github.com/plutopulp/rheo
Project-URL: Repository, https://github.com/plutopulp/rheo
